ninja_bear/__init__.py
ninja_bear/cli.py
ninja_bear/base/__init__.py
ninja_bear/base/config.py
ninja_bear/base/config_file_info.py
ninja_bear/base/configuration_base.py
ninja_bear/base/distribute_info.py
ninja_bear/base/distributor_base.py
ninja_bear/base/distributor_credentials.py
ninja_bear/base/dump_info.py
ninja_bear/base/generator_base.py
ninja_bear/base/generator_configuration.py
ninja_bear/base/generator_naming_conventions.py
ninja_bear/base/info.py
ninja_bear/base/language_config_base.py
ninja_bear/base/language_config_configuration.py
ninja_bear/base/language_config_naming_conventions.py
ninja_bear/base/meta_data_settings.py
ninja_bear/base/name_converter.py
ninja_bear/base/orchestrator.py
ninja_bear/base/plugin_manager.py
ninja_bear/base/property.py
ninja_bear/base/property_type.py
ninja_bear/helpers/__init__.py
ninja_bear/helpers/package_handling.py
ninja_bear-0.1.4.dist-info/LICENSE
ninja_bear-0.1.4.dist-info/METADATA
ninja_bear-0.1.4.dist-info/WHEEL
ninja_bear-0.1.4.dist-info/entry_points.txt
ninja_bear-0.1.4.dist-info/top_level.txt
ninja_bear-0.1.4.dist-info/RECORD
