Metadata-Version: 2.1
Name: ninja-bear
Version: 0.1.4
Summary: ninja-bear keeps your language specific constants in sync
Home-page: https://github.com/monstermichl/ninja-bear.git
Author: monstermichl
Keywords: ninja-bear,constants,language,generator,distributor
Classifier: Programming Language :: Python :: 3
Classifier: License :: OSI Approved :: MIT License
Classifier: Operating System :: OS Independent
Requires-Python: >=3.10
License-File: LICENSE
Requires-Dist: pyyaml>=6.0.1
Requires-Dist: schema>=0.7.5
Requires-Dist: importlib-metadata>=8.5.0
Provides-Extra: dev
Requires-Dist: wheel>=0.41.1; extra == "dev"
Requires-Dist: twine>=4.0.2; extra == "dev"
Requires-Dist: ruff>=0.0.47; extra == "dev"
Requires-Dist: coverage>=7.2.7; extra == "dev"
